xfilios/__init__.py
xfilios/docx.py
xfilios/excel.py
xfilios/exceptions.py
xfilios/handler.py
xfilios/html.py
xfilios/table.py
xfilios-0.0.4.dist-info/LICENSE
xfilios-0.0.4.dist-info/METADATA
xfilios-0.0.4.dist-info/WHEEL
xfilios-0.0.4.dist-info/top_level.txt
xfilios-0.0.4.dist-info/RECORD
