Metadata-Version: 2.1
Name: xfilios
Version: 0.0.4
Summary: Docx and Excel File handler for Streamlit or Dash
Home-page: https://github.com/DataPsycho/xfilios
Author: Data Psycho
Author-email: mr.data.psycho@gmail.com
License: MIT
Keywords: FileIO,Docx,Excel,Streamlit,Dash
Platform: UNKNOWN
Classifier: Programming Language :: Python :: 3 :: Only
Classifier: Programming Language :: Python :: 3.8
Classifier: Programming Language :: Python :: 3.9
Classifier: Development Status :: 4 - Beta
Classifier: Environment :: MacOS X
License-File: LICENSE
Requires-Dist: python-docx (==0.8.11)
Requires-Dist: pandas (==1.3.3)
Requires-Dist: openpyxl (==3.0.9)
